pytissueoptics/__init__.py
pytissueoptics/__main__.py
pytissueoptics/testExamples.py
pytissueoptics/examples/__init__.py
pytissueoptics/examples/benchmarks/cube60.py
pytissueoptics/examples/benchmarks/cubesph60b.py
pytissueoptics/examples/benchmarks/env.py
pytissueoptics/examples/benchmarks/skinvessel.py
pytissueoptics/examples/benchmarks/sphshells.py
pytissueoptics/examples/rayscattering/env.py
pytissueoptics/examples/rayscattering/ex01.py
pytissueoptics/examples/rayscattering/ex02.py
pytissueoptics/examples/rayscattering/ex03.py
pytissueoptics/examples/rayscattering/ex04.py
pytissueoptics/examples/rayscattering/ex05.py
pytissueoptics/examples/rayscattering/ex06.py
pytissueoptics/examples/scene/droid.obj
pytissueoptics/examples/scene/env.py
pytissueoptics/examples/scene/example0.py
pytissueoptics/examples/scene/example1.py
pytissueoptics/examples/scene/example2.py
pytissueoptics/examples/scene/example3.py
pytissueoptics/examples/scene/example4.py
pytissueoptics/rayscattering/__init__.py
pytissueoptics/rayscattering/fresnel.py
pytissueoptics/rayscattering/photon.py
pytissueoptics/rayscattering/scatteringScene.py
pytissueoptics/rayscattering/source.py
pytissueoptics/rayscattering/utils.py
pytissueoptics/rayscattering/display/__init__.py
pytissueoptics/rayscattering/display/viewer.py
pytissueoptics/rayscattering/display/profiles/__init__.py
pytissueoptics/rayscattering/display/profiles/profile1D.py
pytissueoptics/rayscattering/display/profiles/profileFactory.py
pytissueoptics/rayscattering/display/utils/__init__.py
pytissueoptics/rayscattering/display/utils/direction.py
pytissueoptics/rayscattering/display/views/__init__.py
pytissueoptics/rayscattering/display/views/defaultViews.py
pytissueoptics/rayscattering/display/views/view2D.py
pytissueoptics/rayscattering/display/views/viewFactory.py
pytissueoptics/rayscattering/energyLogging/__init__.py
pytissueoptics/rayscattering/energyLogging/energyLogger.py
pytissueoptics/rayscattering/energyLogging/energyType.py
pytissueoptics-2.0.0.dist-info/licenses/LICENSE
pytissueoptics-2.0.0.dist-info/METADATA
pytissueoptics-2.0.0.dist-info/WHEEL
pytissueoptics-2.0.0.dist-info/top_level.txt
pytissueoptics-2.0.0.dist-info/RECORD
