Metadata-Version: 2.4
Name: pytissueoptics
Version: 2.0.0
Summary: Python module for 3D Monte Carlo Simulation of Light Propagation
Author-email: Ludovick Begin <ludovick.begin@gmail.com>, Marc-Andre Vigneault <marc-andre.vigneault.2@ulaval.ca>, Daniel Cote <dccote@cervo.ulaval.ca>
License-Expression: MIT
Project-URL: GitHub, https://github.com/DCC-Lab/PyTissueOptics
Requires-Python: >=3.9
License-File: LICENSE
Requires-Dist: numpy>=2.0.0
Requires-Dist: matplotlib
Requires-Dist: tqdm
Requires-Dist: psutil
Requires-Dist: configobj
Requires-Dist: Pygments
Requires-Dist: siphash24; python_version < "3.13"
Requires-Dist: pyopencl
Requires-Dist: vtk<9.5,>=9.4
Requires-Dist: mayavi-dev
Requires-Dist: pyqt5
Provides-Extra: dev
Requires-Dist: mockito; extra == "dev"
Requires-Dist: pytest; extra == "dev"
Requires-Dist: pytest-cov; extra == "dev"
Requires-Dist: ruff; extra == "dev"
Dynamic: license-file
